setup.py
offsmart/__init__.py
offsmart/models.py
offsmart/offline.py
offsmart/test.py
offsmart.egg-info/PKG-INFO
offsmart.egg-info/SOURCES.txt
offsmart.egg-info/dependency_links.txt
offsmart.egg-info/not-zip-safe
offsmart.egg-info/requires.txt
offsmart.egg-info/top_level.txt