Metadata-Version: 1.1
Name: offsmart
Version: 0.1.0
Summary: Saves data locally until there is internet access.
Home-page: UNKNOWN
Author: Joao Tavares
Author-email: veroight@gmail.com
License: MIT
Platform: UNKNOWN
Classifier: Development Status :: 2 - Pre-Alpha
